{
  "gamePk": 823473,
  "gameDate": "2026-04-28T22:40:00Z",
  "venue": {
    "available": true,
    "name": "Citizens Bank Park",
    "roof": "open",
    "pf_runs": 103,
    "pf_hr_lhb": 109,
    "pf_hr_rhb": 108
  },
  "weather": {
    "available": true,
    "indoor": false,
    "park": "Citizens Bank Park",
    "first_pitch_iso": "2026-04-28T22:40:00Z",
    "temp_f": 56.0,
    "humidity_pct": 42,
    "dew_point_f": 33.2,
    "wind_mph": 5.7,
    "wind_dir_deg": 121,
    "wind_effect": {
      "effect": "cross",
      "delta_runs": 0.0,
      "angle_off_cf": 76
    },
    "precip_prob_pct": 0
  },
  "away": {
    "team_id": 137,
    "team_name": "San Francisco Giants",
    "probable_pitcher_id": 641816,
    "probable_pitcher_name": "Tyler Mahle",
    "pitcher_profile": {
      "id": 641816,
      "available": true,
      "window_days": 30,
      "throws": "R",
      "total_pitches": 365,
      "season_avg_velo": 89.4,
      "starts": [
        {
          "game_date": "2026-04-22",
          "pitches": 91,
          "avg_velo": 90.12307692307694,
          "max_velo": 95.4,
          "csw": 0.34065934065934067,
          "hard_hit": 0.07692307692307693,
          "barrel": 0.0
        },
        {
          "game_date": "2026-04-15",
          "pitches": 89,
          "avg_velo": 88.72022471910113,
          "max_velo": 94.6,
          "csw": 0.2696629213483146,
          "hard_hit": 0.0898876404494382,
          "barrel": 0.056179775280898875
        },
        {
          "game_date": "2026-04-08",
          "pitches": 94,
          "avg_velo": 89.7468085106383,
          "max_velo": 94.9,
          "csw": 0.2553191489361702,
          "hard_hit": 0.02127659574468085,
          "barrel": 0.0
        },
        {
          "game_date": "2026-04-03",
          "pitches": 91,
          "avg_velo": 88.99340659340659,
          "max_velo": 93.5,
          "csw": 0.31868131868131866,
          "hard_hit": 0.07692307692307693,
          "barrel": 0.02197802197802198
        }
      ],
      "pitch_mix": {
        "FC": 0.17,
        "FF": 0.46,
        "FS": 0.236,
        "SI": 0.047,
        "SL": 0.088
      },
      "splits": {
        "L": {
          "pitches": 166,
          "avg_velo": 89.28,
          "csw": 0.343,
          "xwoba": 0.271,
          "hard_hit_rate": 0.066
        },
        "R": {
          "pitches": 199,
          "avg_velo": 89.51,
          "csw": 0.256,
          "xwoba": 0.453,
          "hard_hit_rate": 0.065
        }
      }
    },
    "bullpen_usage": {
      "team_id": 137,
      "window_days": 7,
      "relievers": {
        "676254": {
          "name": "Ryan Walker",
          "appearances": 3,
          "pitches": 43,
          "ip": 3.0,
          "dates": [
            "2026-04-22",
            "2026-04-23",
            "2026-04-25"
          ],
          "back_to_back": true,
          "pitched_yesterday": false
        },
        "621366": {
          "name": "Ryan Borucki",
          "appearances": 2,
          "pitches": 34,
          "ip": 2.0,
          "dates": [
            "2026-04-22",
            "2026-04-25"
          ],
          "back_to_back": false,
          "pitched_yesterday": false
        },
        "669062": {
          "name": "Erik Miller",
          "appearances": 3,
          "pitches": 59,
          "ip": 3.1,
          "dates": [
            "2026-04-22",
            "2026-04-25",
            "2026-04-26"
          ],
          "back_to_back": true,
          "pitched_yesterday": false
        },
        "657424": {
          "name": "Matt Gage",
          "appearances": 2,
          "pitches": 37,
          "ip": 1.2,
          "dates": [
            "2026-04-22",
            "2026-04-25"
          ],
          "back_to_back": false,
          "pitched_yesterday": false
        },
        "676775": {
          "name": "Keaton Winn",
          "appearances": 2,
          "pitches": 16,
          "ip": 1.1,
          "dates": [
            "2026-04-22",
            "2026-04-25"
          ],
          "back_to_back": false,
          "pitched_yesterday": false
        },
        "668873": {
          "name": "Caleb Kilian",
          "appearances": 2,
          "pitches": 31,
          "ip": 2.0,
          "dates": [
            "2026-04-23",
            "2026-04-25"
          ],
          "back_to_back": false,
          "pitched_yesterday": false
        },
        "694918": {
          "name": "Blade Tidwell",
          "appearances": 1,
          "pitches": 25,
          "ip": 2.0,
          "dates": [
            "2026-04-23"
          ],
          "back_to_back": false,
          "pitched_yesterday": false
        },
        "664141": {
          "name": "JT Brubaker",
          "appearances": 1,
          "pitches": 54,
          "ip": 3.0,
          "dates": [
            "2026-04-25"
          ],
          "back_to_back": false,
          "pitched_yesterday": false
        }
      },
      "quality": {
        "bp_innings": 18.33,
        "bp_era": 0.49,
        "bp_k_pct": 0.173,
        "bp_bb_pct": 0.12,
        "bp_whip": 1.09
      }
    },
    "recent_form": {
      "team_id": 137,
      "window_days": 14,
      "games_played": 12,
      "wins": 7,
      "losses": 5,
      "rpg_for": 3.83,
      "rpg_against": 3.5,
      "win_pct": 0.583,
      "results": [
        {
          "date": "2026-04-19",
          "for": 0,
          "against": 3,
          "won": false
        },
        {
          "date": "2026-04-22",
          "for": 3,
          "against": 1,
          "won": true
        },
        {
          "date": "2026-04-23",
          "for": 3,
          "against": 0,
          "won": true
        },
        {
          "date": "2026-04-23",
          "for": 0,
          "against": 3,
          "won": false
        },
        {
          "date": "2026-04-25",
          "for": 4,
          "against": 9,
          "won": false
        },
        {
          "date": "2026-04-25",
          "for": 6,
          "against": 2,
          "won": true
        },
        {
          "date": "2026-04-26",
          "for": 6,
          "against": 3,
          "won": true
        }
      ]
    },
    "top_of_order": {
      "available": false,
      "reason": "no_lineup"
    }
  },
  "home": {
    "team_id": 143,
    "team_name": "Philadelphia Phillies",
    "probable_pitcher_id": 666200,
    "probable_pitcher_name": "Jes\u00fas Luzardo",
    "pitcher_profile": {
      "id": 666200,
      "available": true,
      "window_days": 30,
      "throws": "L",
      "total_pitches": 482,
      "season_avg_velo": 91.14,
      "starts": [
        {
          "game_date": "2026-04-21",
          "pitches": 100,
          "avg_velo": 91.225,
          "max_velo": 99.1,
          "csw": 0.26,
          "hard_hit": 0.07,
          "barrel": 0.01
        },
        {
          "game_date": "2026-04-15",
          "pitches": 98,
          "avg_velo": 92.14285714285714,
          "max_velo": 99.2,
          "csw": 0.30612244897959184,
          "hard_hit": 0.11224489795918367,
          "barrel": 0.01020408163265306
        },
        {
          "game_date": "2026-04-10",
          "pitches": 86,
          "avg_velo": 91.42790697674418,
          "max_velo": 98.6,
          "csw": 0.3372093023255814,
          "hard_hit": 0.023255813953488372,
          "barrel": 0.0
        },
        {
          "game_date": "2026-04-04",
          "pitches": 99,
          "avg_velo": 90.58484848484848,
          "max_velo": 98.6,
          "csw": 0.35353535353535354,
          "hard_hit": 0.020202020202020204,
          "barrel": 0.010101010101010102
        },
        {
          "game_date": "2026-03-29",
          "pitches": 99,
          "avg_velo": 90.34444444444445,
          "max_velo": 97.9,
          "csw": 0.32323232323232326,
          "hard_hit": 0.06060606060606061,
          "barrel": 0.020202020202020204
        }
      ],
      "pitch_mix": {
        "CH": 0.212,
        "FF": 0.255,
        "SI": 0.176,
        "ST": 0.357
      },
      "splits": {
        "L": {
          "pitches": 85,
          "avg_velo": 92.76,
          "csw": 0.247,
          "xwoba": 0.289,
          "hard_hit_rate": 0.094
        },
        "R": {
          "pitches": 397,
          "avg_velo": 90.79,
          "csw": 0.33,
          "xwoba": 0.327,
          "hard_hit_rate": 0.05
        }
      }
    },
    "bullpen_usage": {
      "team_id": 143,
      "window_days": 7,
      "relievers": {
        "641835": {
          "name": "Tim Mayza",
          "appearances": 3,
          "pitches": 61,
          "ip": 3.0,
          "dates": [
            "2026-04-21",
            "2026-04-24",
            "2026-04-26"
          ],
          "back_to_back": false,
          "pitched_yesterday": false
        },
        "621383": {
          "name": "Tanner Banks",
          "appearances": 3,
          "pitches": 52,
          "ip": 1.1,
          "dates": [
            "2026-04-21",
            "2026-04-23",
            "2026-04-25"
          ],
          "back_to_back": false,
          "pitched_yesterday": false
        },
        "641745": {
          "name": "Brad Keller",
          "appearances": 3,
          "pitches": 28,
          "ip": 2.3,
          "dates": [
            "2026-04-21",
            "2026-04-23",
            "2026-04-25"
          ],
          "back_to_back": false,
          "pitched_yesterday": false
        },
        "621237": {
          "name": "Jos\u00e9 Alvarado",
          "appearances": 3,
          "pitches": 50,
          "ip": 2.2,
          "dates": [
            "2026-04-21",
            "2026-04-23",
            "2026-04-25"
          ],
          "back_to_back": false,
          "pitched_yesterday": false
        },
        "689147": {
          "name": "Orion Kerkering",
          "appearances": 3,
          "pitches": 52,
          "ip": 2.2,
          "dates": [
            "2026-04-21",
            "2026-04-23",
            "2026-04-25"
          ],
          "back_to_back": false,
          "pitched_yesterday": false
        },
        "660604": {
          "name": "Alan Rangel",
          "appearances": 1,
          "pitches": 44,
          "ip": 3.0,
          "dates": [
            "2026-04-22"
          ],
          "back_to_back": false,
          "pitched_yesterday": false
        },
        "679775": {
          "name": "Kyle Backhus",
          "appearances": 3,
          "pitches": 39,
          "ip": 3.0,
          "dates": [
            "2026-04-22",
            "2026-04-24",
            "2026-04-25"
          ],
          "back_to_back": true,
          "pitched_yesterday": false
        },
        "663767": {
          "name": "Chase Shugart",
          "appearances": 3,
          "pitches": 20,
          "ip": 1.3,
          "dates": [
            "2026-04-23",
            "2026-04-24",
            "2026-04-26"
          ],
          "back_to_back": true,
          "pitched_yesterday": false
        },
        "676510": {
          "name": "Nolan Hoffman",
          "appearances": 1,
          "pitches": 15,
          "ip": 1.1,
          "dates": [
            "2026-04-26"
          ],
          "back_to_back": false,
          "pitched_yesterday": false
        }
      },
      "quality": {
        "bp_innings": 22.0,
        "bp_era": 4.5,
        "bp_k_pct": 0.16,
        "bp_bb_pct": 0.104,
        "bp_whip": 1.77
      }
    },
    "recent_form": {
      "team_id": 143,
      "window_days": 14,
      "games_played": 12,
      "wins": 1,
      "losses": 11,
      "rpg_for": 3.0,
      "rpg_against": 6.67,
      "win_pct": 0.083,
      "results": [
        {
          "date": "2026-04-20",
          "for": 1,
          "against": 5,
          "won": false
        },
        {
          "date": "2026-04-21",
          "for": 4,
          "against": 7,
          "won": false
        },
        {
          "date": "2026-04-22",
          "for": 2,
          "against": 7,
          "won": false
        },
        {
          "date": "2026-04-23",
          "for": 7,
          "against": 8,
          "won": false
        },
        {
          "date": "2026-04-24",
          "for": 3,
          "against": 5,
          "won": false
        },
        {
          "date": "2026-04-25",
          "for": 8,
          "against": 5,
          "won": true
        },
        {
          "date": "2026-04-26",
          "for": 2,
          "against": 6,
          "won": false
        }
      ]
    },
    "top_of_order": {
      "available": false,
      "reason": "no_lineup"
    }
  },
  "lineups": {
    "lineups_confirmed": false,
    "away_lineup": [],
    "home_lineup": [],
    "umpires": []
  }
}